llm_utils/__init__.py
llm_utils/chat_format.py
llm_utils/group_messages.py
llm_utils/lm.py
llm_utils/lm_classification.py
llm_utils/load_chat_dataset.py
llm_utils/scripts/vllm_load_balancer.py
llm_utils/scripts/vllm_serve.py
speedy_llm_utils-1.1.10.dist-info/METADATA
speedy_llm_utils-1.1.10.dist-info/WHEEL
speedy_llm_utils-1.1.10.dist-info/entry_points.txt
speedy_llm_utils-1.1.10.dist-info/RECORD
