Metadata-Version: 2.3
Name: speedy_llm_utils
Version: 1.1.10
Summary: Utility functions for LLM applications
Author: Anh Vo
Requires-Python: >=3.9,<4.0
Classifier: Programming Language :: Python :: 3
Classifier: Programming Language :: Python :: 3.9
Classifier: Programming Language :: Python :: 3.10
Classifier: Programming Language :: Python :: 3.11
Classifier: Programming Language :: Python :: 3.12
Classifier: Programming Language :: Python :: 3.13
Requires-Dist: dspy
Requires-Dist: google-generativeai (>=0.8.4,<0.9.0)
Requires-Dist: json-repair (>=0.40.0,<0.41.0)
Requires-Dist: langchain (>=0.3.20,<0.4.0)
Requires-Dist: langchain-core (>=0.3.41,<0.4.0)
Requires-Dist: langchain-openai (>=0.3.7,<0.4.0)
Requires-Dist: numpy
Requires-Dist: pandas
Requires-Dist: transformers (>=4.49.0,<5.0.0)
Project-URL: Homepage, https://github.com/anhvth/llm_utils
